uk_grid_intensity/__init__.py
uk_grid_intensity/_version.py
uk_grid_intensity/cli.py
uk_grid_intensity/client.py
uk_grid_intensity/constants.py
uk_grid_intensity/schemas.py
uk_grid_intensity-0.1.1.dist-info/METADATA
uk_grid_intensity-0.1.1.dist-info/WHEEL
uk_grid_intensity-0.1.1.dist-info/entry_points.txt
uk_grid_intensity-0.1.1.dist-info/licenses/LICENSE
uk_grid_intensity-0.1.1.dist-info/RECORD
