Metadata-Version: 2.4
Name: uk-grid-intensity
Version: 0.1.1
Summary: Python client for the UK National Grid Carbon Intensity API
Project-URL: Homepage, https://github.com/cdinu/uk-grid-intensity-py
Project-URL: Repository, https://github.com/cdinu/uk-grid-intensity-py
Project-URL: Documentation, https://github.com/cdinu/uk-grid-intensity-py#readme
Project-URL: Bug Tracker, https://github.com/cdinu/uk-grid-intensity-py/issues
Author-email: Cristian Dinu <c.dinu@ucl.ac.uk>
License-File: LICENSE
Keywords: api,carbon,energy,grid,intensity,uk
Classifier: Development Status :: 4 - Beta
Classifier: Intended Audience :: Developers
Classifier: License :: OSI Approved :: MIT License
Classifier: Operating System :: OS Independent
Classifier: Programming Language :: Python :: 3
Classifier: Programming Language :: Python :: 3.8
Classifier: Programming Language :: Python :: 3.9
Classifier: Programming Language :: Python :: 3.10
Classifier: Programming Language :: Python :: 3.11
Classifier: Programming Language :: Python :: 3.12
Classifier: Programming Language :: Python :: 3.13
Classifier: Topic :: Scientific/Engineering
Classifier: Topic :: Software Development :: Libraries :: Python Modules
Classifier: Topic :: Utilities
Requires-Python: >=3.8
Requires-Dist: httpx>=0.24.0
Requires-Dist: pydantic>=2.0.0
Requires-Dist: typing-extensions>=4.0.0; python_version < '3.11'
Provides-Extra: dev
Requires-Dist: black>=23.0.0; extra == 'dev'
Requires-Dist: isort>=5.0.0; extra == 'dev'
Requires-Dist: mypy>=1.0.0; extra == 'dev'
Requires-Dist: pytest-asyncio>=0.21.0; extra == 'dev'
Requires-Dist: pytest-httpx>=0.21.0; extra == 'dev'
Requires-Dist: pytest>=7.0.0; extra == 'dev'
Requires-Dist: ruff>=0.1.0; extra == 'dev'
